jog/__init__.py
jog/elk.py
jog-0.1.1.dist-info/DESCRIPTION.rst
jog-0.1.1.dist-info/METADATA
jog-0.1.1.dist-info/RECORD
jog-0.1.1.dist-info/WHEEL
jog-0.1.1.dist-info/metadata.json
jog-0.1.1.dist-info/top_level.txt
