Metadata-Version: 2.0
Name: jog
Version: 0.1.1
Summary: JSON Structured Logging for Python
Home-page: https://github.com/Braedon/python-jog
Author: Braedon Vickers
Author-email: braedon.vickers@gmail.com
License: MIT
Keywords: logging log json structured logstash
Platform: UNKNOWN
Classifier: Development Status :: 4 - Beta
Classifier: Intended Audience :: Developers
Classifier: Topic :: System :: Logging
Classifier: License :: OSI Approved :: MIT License
Classifier: Programming Language :: Python :: 3
Classifier: Programming Language :: Python :: 2
